rainiee_algorithm/__init__.py
rainiee_algorithm/rainiee_algorithm_client.py
rainiee_algorithm/base/__init__.py
rainiee_algorithm/base/client.py
rainiee_algorithm/base/data_pro.py
rainiee_algorithm/base/login.py
rainiee_algorithm/portfolio/__init__.py
rainiee_algorithm/portfolio/portfolio_api.py
rainiee_algorithm/utils/__init__.py
rainiee_algorithm/utils/upass.py
rainiee_decision_engine/__init__.py
rainiee_decision_engine/decision_engine_client.py
rainiee_decision_engine/base/__init__.py
rainiee_decision_engine/base/client.py
rainiee_decision_engine/base/data_pro.py
rainiee_decision_engine/base/login.py
rainiee_decision_engine/portfolio/__init__.py
rainiee_decision_engine/portfolio/portfolio_api.py
rainiee_decision_engine/utils/__init__.py
rainiee_decision_engine/utils/upass.py
rainiee_decision_engine-2.1.0.dist-info/METADATA
rainiee_decision_engine-2.1.0.dist-info/WHEEL
rainiee_decision_engine-2.1.0.dist-info/top_level.txt
rainiee_decision_engine-2.1.0.dist-info/RECORD
